cereeberus/__init__.py
cereeberus/compute/__init__.py
cereeberus/compute/computereeb.py
cereeberus/compute/draw.py
cereeberus/compute/unionfind.py
cereeberus/compute/utils.py
cereeberus/compute/Old/degree.py
cereeberus/compute/Old/distance.py
cereeberus/compute/Old/merge.py
cereeberus/compute/Old/merge_class.py
cereeberus/compute/Old/uf.py
cereeberus/data/__init__.py
cereeberus/data/ex_embedgraphs.py
cereeberus/data/ex_graphs.py
cereeberus/data/ex_mappergraphs.py
cereeberus/data/ex_mergetrees.py
cereeberus/data/ex_reebgraphs.py
cereeberus/data/ex_torus.py
cereeberus/data/rand_gen_mappergraphs.py
cereeberus/data/shapes.py
cereeberus/distance/__init__.py
cereeberus/distance/ilp.py
cereeberus/distance/interleave.py
cereeberus/distance/labeled_blocks.py
cereeberus/reeb/__init__.py
cereeberus/reeb/embeddedgraph.py
cereeberus/reeb/lowerstar.py
cereeberus/reeb/mapper.py
cereeberus/reeb/merge.py
cereeberus/reeb/reebgraph.py
cereeberus-0.1.9.dist-info/licenses/LICENSE
cereeberus-0.1.9.dist-info/METADATA
cereeberus-0.1.9.dist-info/WHEEL
cereeberus-0.1.9.dist-info/top_level.txt
cereeberus-0.1.9.dist-info/RECORD
