Metadata-Version: 2.4
Name: cereeberus
Version: 0.1.9
Summary: A Python package for Reeb graphs
Author-email: Liz Munch <muncheli@msu.edu>
Project-URL: repository, https://github.com/MunchLab/ceREEBerus
Project-URL: homepage, https://munchlab.github.io/ceREEBerus/
Project-URL: documentation, https://munchlab.github.io/ceREEBerus/
Classifier: Programming Language :: Python :: 3
Classifier: Operating System :: OS Independent
Requires-Python: >=3.7
License-File: LICENSE
Requires-Dist: numpy
Requires-Dist: networkx
Requires-Dist: matplotlib
Requires-Dist: pandas
Requires-Dist: scipy
Requires-Dist: pulp
Requires-Dist: gudhi
Dynamic: license-file
